ajenti_plugin_cpu_temp/__init__.py
ajenti_plugin_cpu_temp/main.py
ajenti_plugin_cpu_temp/plugin.yml
ajenti_plugin_cpu_temp/resources/build/all.css
ajenti_plugin_cpu_temp/resources/build/all.js
ajenti_plugin_cpu_temp/resources/build/all.vendor.css
ajenti_plugin_cpu_temp/resources/build/all.vendor.js
ajenti_plugin_cpu_temp/resources/extra-vendor/chart.js/Chart.bundle.min.js
ajenti_plugin_cpu_temp/resources/extra-vendor/chart.js/Chart.min.css
ajenti_plugin_cpu_temp/resources/extra-vendor/chart.js/Chart.min.js
ajenti_plugin_cpu_temp/resources/js/module.coffee
ajenti_plugin_cpu_temp/resources/js/module/dash.controller.coffee
ajenti_plugin_cpu_temp/resources/partials/dash.html
ajenti_plugin_cpu_temp/resources/partials/config/dash.config.html
ajenti.plugin.cpu_temp-0.0.4.dist-info/LICENSE.txt
ajenti.plugin.cpu_temp-0.0.4.dist-info/METADATA
ajenti.plugin.cpu_temp-0.0.4.dist-info/WHEEL
ajenti.plugin.cpu_temp-0.0.4.dist-info/top_level.txt
ajenti.plugin.cpu_temp-0.0.4.dist-info/RECORD
